a_selenium_absolute_screencoords/LICENSE
a_selenium_absolute_screencoords/README.MD
a_selenium_absolute_screencoords/__init__.py
a_selenium_absolute_screencoords/requirements.txt
a_selenium_absolute_screencoords/thirdparty.json
a_selenium_absolute_screencoords-0.10.dist-info/LICENSE.rst
a_selenium_absolute_screencoords-0.10.dist-info/METADATA
a_selenium_absolute_screencoords-0.10.dist-info/WHEEL
a_selenium_absolute_screencoords-0.10.dist-info/top_level.txt
a_selenium_absolute_screencoords-0.10.dist-info/RECORD
