Metadata-Version: 2.1
Name: a-selenium-absolute-screencoords
Version: 0.10
Summary: Calculates the absolute screen coordinates of any Selenium element so that you can click on them with every basic automation tool
Home-page: https://github.com/hansalemaos/a_selenium_absolute_screencoords
Author: Johannes Fischer
Author-email: <aulasparticularesdealemaosp@gmail.com>
License: MIT
Keywords: Selenium,click,interact
Classifier: Development Status :: 4 - Beta
Classifier: Programming Language :: Python :: 3 :: Only
Classifier: Programming Language :: Python :: 3.9
Classifier: Topic :: Scientific/Engineering :: Visualization
Classifier: Topic :: Software Development :: Libraries :: Python Modules
Classifier: Topic :: Text Editors :: Text Processing
Classifier: Topic :: Text Processing :: General
Classifier: Topic :: Text Processing :: Indexing
Classifier: Topic :: Text Processing :: Filters
Classifier: Topic :: Utilities
License-File: LICENSE.rst
Requires-Dist: ctypes-window-info
Requires-Dist: mousekey
